topmodel/__init__.py
topmodel/app.py
topmodel/py.typed
topmodel/check/__init__.py
topmodel/check/amide_bond.py
topmodel/check/chirality.py
topmodel/check/clashes.py
topmodel/check/py.typed
topmodel/util/MMTFParser.py
topmodel/util/__init__.py
topmodel/util/errors.py
topmodel/util/parser.py
topmodel/util/py.typed
topmodel/util/utils.py
protein_topmodel-1.0.1.dist-info/LICENSE
protein_topmodel-1.0.1.dist-info/METADATA
protein_topmodel-1.0.1.dist-info/WHEEL
protein_topmodel-1.0.1.dist-info/entry_points.txt
protein_topmodel-1.0.1.dist-info/top_level.txt
protein_topmodel-1.0.1.dist-info/RECORD
