Metadata-Version: 2.1
Name: protein-topmodel
Version: 1.0.1
Summary: validate molecular structure models
Author: Janik Kokot
License: MIT
Platform: unix
Platform: linux
Platform: osx
Platform: cygwin
Platform: win32
Requires-Python: >=3.8
License-File: LICENSE
Requires-Dist: Click
Requires-Dist: colorama
Requires-Dist: biopython
Requires-Dist: mmtf-python
Requires-Dist: scipy
Requires-Dist: mendeleev
Provides-Extra: testing
Requires-Dist: pytest >=6.0 ; extra == 'testing'
Requires-Dist: pytest-cov >=2.0 ; extra == 'testing'
Requires-Dist: mypy >=0.910 ; extra == 'testing'
Requires-Dist: flake8 >=3.9 ; extra == 'testing'
Requires-Dist: tox >=3.24 ; extra == 'testing'
